setup.py
panorbit_add/__init__.py
panorbit_add/new.py
panorbit_add.egg-info/PKG-INFO
panorbit_add.egg-info/SOURCES.txt
panorbit_add.egg-info/dependency_links.txt
panorbit_add.egg-info/not-zip-safe
panorbit_add.egg-info/requires.txt
panorbit_add.egg-info/top_level.txt