Metadata-Version: 1.0
Name: panorbit-add
Version: 0.1
Summary: basic math function
Home-page: UNKNOWN
Author: panorbit
Author-email: panorbit@example.com
License: MIT
Platform: UNKNOWN
